pistol/__init__.py
pistol/__main__.py
pistol/constants.py
pistol/core.py
pistol/ep.py
pistol/logging.py
pistol/meta.py
pistol/mutable_path.py
pistol/parser.py
pistol/plugins.py
pistol/prop_state.py
pistol/registry.py
pistol/reset_meta.py
pistol/scs_cache.py
pistol/subprocess.py
pistol/timestamp.py
pistol/verbose.py
pistol-2.7.dist-info/LICENSE
pistol-2.7.dist-info/METADATA
pistol-2.7.dist-info/WHEEL
pistol-2.7.dist-info/entry_points.txt
pistol-2.7.dist-info/top_level.txt
pistol-2.7.dist-info/RECORD
